django_simpletask3/__init__.py
django_simpletask3/actions.py
django_simpletask3/admin.py
django_simpletask3/apps.py
django_simpletask3/models.py
django_simpletask3/server.py
django_simpletask3/services.py
django_simpletask3/settings.py
django_simpletask3/simq.py
django_simpletask3/tests.py
django_simpletask3/version.py
django_simpletask3/views.py
django_simpletask3/management/__init__.py
django_simpletask3/management/commands/__init__.py
django_simpletask3/management/commands/django-simpletask3-server.py
django_simpletask3/migrations/__init__.py
django_simpletask3-0.1.3.dist-info/METADATA
django_simpletask3-0.1.3.dist-info/WHEEL
django_simpletask3-0.1.3.dist-info/top_level.txt
django_simpletask3-0.1.3.dist-info/RECORD
