Metadata-Version: 2.1
Name: django-simpletask3
Version: 0.1.3
Summary: 基于Redis及SimQ的异步任务处理。
Author: rRR0VrFP
Maintainer: rRR0VrFP
License: Apache License, Version 2.0
Keywords: django-simpletask3,simqcore
Classifier: Development Status :: 5 - Production/Stable
Classifier: Intended Audience :: Developers
Classifier: Topic :: Software Development :: Libraries :: Python Modules
Classifier: License :: OSI Approved :: Apache Software License
Classifier: Programming Language :: Python :: 3
Classifier: Programming Language :: Python :: 3 :: Only
Requires-Dist: django
Requires-Dist: django-click
Requires-Dist: django-model-helper
Requires-Dist: django-environment-settings
Requires-Dist: simqcore
Requires-Dist: redis
